rouge_score/__init__.py
rouge_score/create_pyrouge_files.py
rouge_score/io.py
rouge_score/io_test.py
rouge_score/rouge.py
rouge_score/rouge_scorer.py
rouge_score/rouge_scorer_test.py
rouge_score/scoring.py
rouge_score/scoring_test.py
rouge_score/test_util.py
rouge_score/tokenize.py
rouge_score/tokenize_test.py
rouge_score-0.0.4.dist-info/METADATA
rouge_score-0.0.4.dist-info/WHEEL
rouge_score-0.0.4.dist-info/top_level.txt
rouge_score-0.0.4.dist-info/RECORD
