Metadata-Version: 2.1
Name: rouge-score
Version: 0.0.4
Summary: Pure python implementation of ROUGE-1.5.5.
Home-page: https://github.com/google-research/google-research/tree/master/rouge
Author: Google LLC
Author-email: no-reply@google.com
License: UNKNOWN
Platform: UNKNOWN
Classifier: Programming Language :: Python :: 3
Classifier: License :: OSI Approved :: Apache Software License
Classifier: Operating System :: OS Independent
Requires-Python: >=2.7
